aihqrating/__init__.py
aihqrating/flant5_rating.py
aihqrating/install_packages.py
aihqrating/main.py
aihqrating/docs/Makefile
aihqrating/docs/make.bat
aihqrating/templates/session.html
aihqrating-0.0.7.dist-info/METADATA
aihqrating-0.0.7.dist-info/WHEEL
aihqrating-0.0.7.dist-info/top_level.txt
aihqrating-0.0.7.dist-info/RECORD
