Metadata-Version: 2.1
Name: aihqrating
Version: 0.0.7
Summary: TBD
Author: Louisa
Author-email: evanszhu2001@gmail.com
Classifier: License :: OSI Approved :: MIT License
Classifier: Programming Language :: Python :: 3
Classifier: Programming Language :: Python :: 3.6
Classifier: Programming Language :: Python :: 3.7
Classifier: Programming Language :: Python :: 3.8
Classifier: Programming Language :: Python :: 3.9
Requires-Dist: numpy
Requires-Dist: matplotlib
Requires-Dist: scipy
Requires-Dist: pandas
Requires-Dist: scikit-learn
Requires-Dist: Werkzeug ==2.3.8
Requires-Dist: Flask ==2.2.2
Requires-Dist: Flask-SocketIO ==5.3.6
Requires-Dist: sentencepiece ==0.2.0
Requires-Dist: torch ==2.0.1
Requires-Dist: transformers ==4.29.2
Requires-Dist: openai ==1.18.0
